{
  "type": "DXVK",
  "versionName": "",
  "versionCode": 0,
  "description": "",
  "files": [
  	{
      "source": "system32/d3d9.dll",
      "target": "${system32}/d3d9.dll"
    },
	    {
      "source": "system32/d3d10core.dll",
      "target": "${system32}/d3d10core.dll"
    },
	    {
      "source": "system32/d3d11.dll",
      "target": "${system32}/d3d11.dll"
    },
	    {
      "source": "system32/dxgi.dll",
      "target": "${system32}/dxgi.dll"
    },
  	{
      "source": "syswow64/d3d9.dll",
      "target": "${syswow64}/d3d9.dll"
    },
	    {
      "source": "syswow64/d3d10core.dll",
      "target": "${syswow64}/d3d10core.dll"
    },
	    {
      "source": "syswow64/d3d11.dll",
      "target": "${syswow64}/d3d11.dll"
    },
	    {
      "source": "syswow64/dxgi.dll",
      "target": "${syswow64}/dxgi.dll"
    }
  ]
}
